<Defs>
    <XmlExtensions.SettingsMenuDef>
        <modId>boomer.Rebalance</modId>
        <label>(BL) Rebalance</label>
        <settings>
            <li Class="XmlExtensions.Setting.TabView">
                <tabs>
                    <li>
                        <label>Core</label>
                        <settings>
                            <li Class="XmlExtensions.Setting.Gap" />
                            <!--Behavior-->
                            <li Class="XmlExtensions.Setting.Text">
                                <anchor>Middle</anchor>
                                <text>Behavior</text>
                                <tKey>BLRebalanceBehavior</tKey>
                            </li>
                            <li Class="XmlExtensions.Setting.Checkbox">
                                <key>doNotDigOutIfCannotReachMapEdge</key>
                                <label>Animals Do Not Mine to Escape</label>
                                <tooltip>Animals will no longer break through walls when they are hungry.</tooltip>
                                <defaultValue>false</defaultValue>
                            </li>
                            <li Class="XmlExtensions.Setting.Checkbox">
                                <key>lessPreferableInsectJelly</key>
                                <label>Less Preferable Insect Jelly</label>
                                <tooltip>Moves insect jelly to the rawTasty preferability alongide berries.</tooltip>
                                <defaultValue>false</defaultValue>
                            </li>
                            <li Class="XmlExtensions.Setting.Checkbox">
                                <key>enemiesDoNotFlee</key>
                                <label>Permanent Enemies Do Not Flee</label>
                                <tooltip>Raiders from permanently hostile factions like pirates won't flee when they're losing the fight.</tooltip>
                                <defaultValue>false</defaultValue>
                            </li>
                            <!--Colonist-->
                            <li Class="XmlExtensions.Setting.Text">
                                <anchor>Middle</anchor>
                                <text>Colonist</text>
                                <tKey>BLRebalanceWorldGen</tKey>
                            </li>
                            <li Class="XmlExtensions.Setting.Checkbox">
                                <key>spouseOpinion</key>
                                <label>Buff Spouse Opinion</label>
                                <tooltip>Increases the spouse opinion moodlet to +100 to lower the likelihood of divorce. Ought to be -100 though.</tooltip>
                                <defaultValue>false</defaultValue>
                            </li>
                            <li Class="XmlExtensions.Setting.Checkbox">
                                <key>noBanishedMoodDebuff</key>
                                <label>Remove Mood Debuff for Banishing Colonists</label>
                                <tooltip>Removes all moodlets related to banishing colonists/prisoners/animals and rejecting joiners.</tooltip>
                                <defaultValue>false</defaultValue>
                            </li>
                            <!--Pawn Generation-->
                            <li Class="XmlExtensions.Setting.Text">
                                <anchor>Middle</anchor>
                                <text>Pawn Generation</text>
                                <tKey>BLRebalancePawnGeneration</tKey>
                            </li>
                            <li Class="XmlExtensions.Setting.Checkbox">
                                <key>fewerBodyFat</key>
                                <label>Fewer Fat Bodies</label>
                                <tooltip>Replaces fat bodies in backstories with normal bodies, significantly lowering their chances of appearing without removing the body outright. Doesn't affect xenotypes with the fat gene.</tooltip>
                                <defaultValue>false</defaultValue>
                            </li>
                            <li Class="XmlExtensions.Setting.Checkbox">
                                <key>fewerBodyHulk</key>
                                <label>Fewer Hulk Bodies</label>
                                <tooltip>Replaces hulk bodies in backstories with normal bodies, significantly lowering their chances of appearing without removing the body outright. Doesn't affect xenotypes with the hulk gene.</tooltip>
                                <defaultValue>false</defaultValue>
                            </li>
                            <li Class="XmlExtensions.Setting.Checkbox">
                                <key>fewerBodyThin</key>
                                <label>Fewer Thin Bodies</label>
                                <tooltip>Replaces thin bodies in backstories with normal bodies, significantly lowering their chances of appearing without removing the body outright. Doesn't affect xenotypes with the thin gene.</tooltip>
                                <defaultValue>false</defaultValue>
                            </li>
                            <li Class="XmlExtensions.Setting.Checkbox">
                                <key>noBeards</key>
                                <label>Remove Beards</label>
                                <tooltip>Removes all beards from the game. Probably not a good idea to enable mid-save.</tooltip>
                                <defaultValue>false</defaultValue>
                            </li>
                            <li Class="XmlExtensions.Setting.Checkbox">
                                <key>fewerHeadsNarrow</key>
                                <label>Remove Narrow Heads</label>
                                <tooltip>Aggressively removes narrow heads from the game. Patching logic works for every mod I've tested. Probably not a good idea to enable mid-save.</tooltip>
                                <defaultValue>false</defaultValue>
                            </li>
                            <li Class="XmlExtensions.Setting.Checkbox">
                                <key>fewerHeadsWideFemale</key>
                                <label>Remove Wide Female Heads</label>
                                <tooltip>Removes the wide female head from the game. Probably not a good idea to enable mid-save.</tooltip>
                                <defaultValue>false</defaultValue>
                            </li>
                            <!--Tweaks-->
                            <li Class="XmlExtensions.Setting.Text">
                                <anchor>Middle</anchor>
                                <text>Tweaks</text>
                                <tKey>BLRebalanceTweaks</tKey>
                            </li>
                            <li Class="XmlExtensions.Setting.Checkbox">
                                <key>hopperStackLimit</key>
                                <label>Increase Hopper Stack Limit</label>
                                <tooltip>Increases the hopper stack limit from 1 to 3.</tooltip>
                                <defaultValue>false</defaultValue>
                            </li>
                            <li Class="XmlExtensions.Setting.Checkbox">
                                <key>apparelCoversHandsAndFeet</key>
                                <label>Most Apparel Covers Hands and Feet</label>
                                <tooltip>Adds foot coverage to vanilla apparel that covers the full leg. Adds hand coverage to vanilla apparel to apparel that covers the full arm. In each case, a note is appended to the description of the apparel.</tooltip>
                                <defaultValue>false</defaultValue>
                            </li>
                            <li Class="XmlExtensions.Setting.Checkbox">
                                <key>noFoodPoisoningConsciousnessDebuff</key>
                                <label>Remove Consciousness Debuff for Food Poisoning</label>
                                <tooltip>Removes the consciousness debuff from food poisoning because consciousness is already affected by the blood filtration debuff and pain.</tooltip>
                                <defaultValue>false</defaultValue>
                            </li>
                            <li Class="XmlExtensions.Setting.Checkbox">
                                <key>noDefaultStorageSettings</key>
                                <label>Remove Default Settings for Storage Buildings</label>
                                <tooltip>Newly built storage buildings will not store any items by default.</tooltip>
                                <defaultValue>false</defaultValue>
                            </li>
                            <li Class="XmlExtensions.Setting.Checkbox">
                                <key>renderHairOverApparel</key>
                                <label>Render Hair Over Apparel</label>
                                <tooltip>Tells the game to render hair over apparel like armor and coats.</tooltip>
                                <defaultValue>false</defaultValue>
                            </li>
                            <li Class="XmlExtensions.Setting.Checkbox">
                                <key>vanometricPowerCell</key>
                                <label>Vanometric Power Cells Are Batteries Too</label>
                                <tooltip>Adds 1000W of 100% efficiency power storage to vanometric power cells.</tooltip>
                                <defaultValue>false</defaultValue>
                            </li>
                            <!--Royalty-->
                            <!--Ideology-->
                        </settings>
                    </li>
                    <li MayRequire="Ludeon.Rimworld.Ideology">
                        <label>Ideology</label>
                        <settings>
                            <li Class="XmlExtensions.Setting.Gap" />
                            <li Class="XmlExtensions.Setting.Checkbox">
                                <key>betterDryads</key>
                                <label>Double Gauranlen Output</label>
                                <tooltip>Doubles the yield for gauranlens like the medicine maker to make them less terrible.</tooltip>
                                <defaultValue>false</defaultValue>
                            </li>
                            <li Class="XmlExtensions.Setting.Checkbox">
                                <key>removeForcedStyles</key>
                                <label>Remove Forced Styles for New Ideologies</label>
                                <tooltip>Newly generated ideologies will not have styles based on their memes or structures. You can still pick styles manually.</tooltip>
                                <defaultValue>false</defaultValue>
                            </li>
                            <li Class="XmlExtensions.Setting.Checkbox">
                                <key>disablePreferredApparel</key>
                                <label>Remove Preferred Apparel for New Ideologies</label>
                                <tooltip>Newly generated ideologies will not have preferred apparel. You can still pick preferred apparel manually.</tooltip>
                                <defaultValue>false</defaultValue>
                            </li>
                            <li Class="XmlExtensions.Setting.Checkbox">
                                <key>noSlaveWorkDisabler</key>
                                <label>Remove Slave Work Disabler</label>
                                <tooltip>Allows slaves to do every work type except for wardening.</tooltip>
                                <defaultValue>false</defaultValue>
                            </li>
                            <li Class="XmlExtensions.Setting.Checkbox">
                                <key>specialistsWork</key>
                                <label>Specialists Can Do More Work</label>
                                <tooltip>Allows specialists to ddo everything with the ManualDumb work tag.</tooltip>
                                <defaultValue>false</defaultValue>
                            </li>
                            <li Class="XmlExtensions.Setting.Slider">
                                <key>gauranlenPruningSpeed</key>
                                <label>Gauranlen Tree Pruning Speed: {gauranlenPruningSpeed} (Default: 0.1)</label>
                                <min>0.1</min>
                                <max>1</max>
                                <decimals>1</decimals>
                                <defaultValue>0.1</defaultValue>
                            </li>
                            <!--Biosculpter Sliders-->
                            <li Class="XmlExtensions.Setting.Text">
                                <anchor>Middle</anchor>
                                <text>Biosculpter</text>
                                <tKey>BLRebalanceBiosculpter</tKey>
                            </li>
                            <li Class="XmlExtensions.Setting.Slider">
                                <key>biosculpterPodAgeReversal</key>
                                <label>Age Reversal Cycle: {biosculpterPodAgeReversal} days (Default: 8)</label>
                                <min>1</min>
                                <max>16</max>
                                <decimals>0</decimals>
                                <defaultValue>8</defaultValue>
                            </li>
                            <li Class="XmlExtensions.Setting.Slider">
                                <key>biosculpterPodMedic</key>
                                <label>Medic Cycle: {biosculpterPodMedic} days (Default: 6)</label>
                                <min>1</min>
                                <max>12</max>
                                <decimals>0</decimals>
                                <defaultValue>6</defaultValue>
                            </li>
                            <li Class="XmlExtensions.Setting.Slider">
                                <key>biosculpterPodPleasure</key>
                                <label>Pleasure Cycle: {biosculpterPodPleasure} days (Default: 4)</label>
                                <min>1</min>
                                <max>8</max>
                                <decimals>0</decimals>
                                <defaultValue>4</defaultValue>
                            </li>
                            <li Class="XmlExtensions.Setting.Slider">
                                <key>biosculpterPodRegeneration</key>
                                <label>Bioregeneration Cycle: {biosculpterPodRegeneration} days (Default: 25)</label>
                                <min>1</min>
                                <max>50</max>
                                <decimals>0</decimals>
                                <defaultValue>25</defaultValue>
                            </li>
                        </settings>
                    </li>
                    <!--Biotech-->
                    <li MayRequire="Ludeon.Rimworld.Biotech">
                        <label>Biotech</label>
                        <settings>
                            <li Class="XmlExtensions.Setting.Gap" />
                            <li Class="XmlExtensions.Setting.Checkbox">
                                <key>moreCapableLifter</key>
                                <label>Allow Lifter Mechanoid To Do More Hauling Jobs</label>
                                <tooltip>Brings lifter mechanoids more in line with human pawns, allowing them to do more hauling and hauling-related like carrying other mechs to a recharger.</tooltip>
                                <defaultValue>false</defaultValue>
                            </li>
                            <li Class="XmlExtensions.Setting.Checkbox">
                                <key>disableExostriderRemains</key>
                                <label>Disable Exostrider Remains on All Scenarios</label>
                                <tooltip>Does exactly what the title says. For some reason it adds the part twice which is harmless but annoying.</tooltip>
                                <defaultValue>false</defaultValue>
                            </li>
                            <li Class="XmlExtensions.Setting.Checkbox">
                                <key>factionReplacers</key>
                                <label>Do Not Replace Core Factions</label>
                                <tooltip>Factions like the impid tribe will no longer replace the fierce tribe by default. Both will appear by default until they are disabled manually.</tooltip>
                                <defaultValue>false</defaultValue>
                            </li>
                            <li Class="XmlExtensions.Setting.Checkbox">
                                <key>wastepackStorageNerf</key>
                                <label>Increase Wastepack Stack Size</label>
                                <tooltip>Also allows wastepacks to be stored on shelves.</tooltip>
                                <defaultValue>false</defaultValue>
                            </li>
                            <li Class="XmlExtensions.Setting.Checkbox">
                                <key>durableMechChips</key>
                                <label>Mech Chips Are Invincible</label>
                                <tooltip>Mechanoid chips dropped by war machines in command of massive mechanoid armies, created by the machine gods of the universe capable of bending time and reality, whose sole purpose in this world is to engage in combat and defeat the its strongest enemies, now won't be destroyed by a stray bolt action rifle round.</tooltip>
                                <defaultValue>false</defaultValue>
                            </li>
                            <li Class="XmlExtensions.Setting.Checkbox">
                                <key>childKillerOpinion</key>
                                <label>Reduce Opinion Offset For Killing Children</label>
                                <tooltip>Reduces the -20 "killed a child" opinion debuff to -6, because sometimes these kids are asking for it.</tooltip>
                                <defaultValue>false</defaultValue>
                            </li>
                            <li Class="XmlExtensions.Setting.Slider">
                                <key>learningRateFactor</key>
                                <label>Child Learning Rate Factor: {learningRateFactor} (Default: 1)</label>
                                <min>0.1</min>
                                <max>5</max>
                                <decimals>1</decimals>
                                <defaultValue>1</defaultValue>
                            </li>
                            <li Class="XmlExtensions.Setting.Slider">
                                <key>pregnancyDuration</key>
                                <label>Pregnancy Duration: {pregnancyDuration} days (Default: 18)</label>
                                <min>1</min>
                                <max>60</max>
                                <decimals>0</decimals>
                                <defaultValue>18</defaultValue>
                            </li>
                        </settings>
                    </li>
                    <!--Anomaly-->
                    <!--Odyssey-->
                    <li MayRequire="Ludeon.Rimworld.Odyssey">
                        <label>Odyssey</label>
                        <settings>
                            <li Class="XmlExtensions.Setting.Gap" />
                            <li Class="XmlExtensions.Setting.Checkbox">
                                <key>fishingResearchNerf</key>
                                <label>Reduce Fishing Research Cost to 200</label>
                                <tooltip>Because researching fishing poles should be easier than researching gravtech.</tooltip>
                                <defaultValue>false</defaultValue>
                            </li>
                            <li Class="XmlExtensions.Setting.Checkbox">
                                <key>fishingWorkType</key>
                                <label>Move Fishing to Its Own Work Type</label>
                                <tooltip>Moves fishing from the hunting work type to its own work type, between crafting and hauling.</tooltip>
                                <defaultValue>false</defaultValue>
                            </li>
                            <li Class="XmlExtensions.Setting.Checkbox">
                                <key>gravshipConduit</key>
                                <label>Gravship Hulls Are Conduits</label>
                                <tooltip>Add the CompPowerTransmitter comp to gravship hulls so that they carry power.</tooltip>
                                <defaultValue>false</defaultValue>
                            </li>
                            <li Class="XmlExtensions.Setting.ToggleableSettings">
                                <key>gravshipConduit</key>
                                <caseTrue>
                                    <li Class="XmlExtensions.Setting.Checkbox">
                                        <key>gravshipConduitNerf</key>
                                        <label>Gravship Hulls Cost 9 Steel</label>
                                        <tooltip>Increases the steel cost of gravship hulls from 7 to 9 to compensate.</tooltip>
                                        <defaultValue>false</defaultValue>
                                        <padLeft>8</padLeft>
                                    </li>
                                </caseTrue>
                            </li>
                        </settings>
                    </li>
                </tabs>
            </li>
        </settings>
    </XmlExtensions.SettingsMenuDef>
</Defs>